README.rst
setup.py
dictcom/__init__.py
dictcom/download.py
dictcom/models.py
dictcom/parse.py
dictcom.egg-info/PKG-INFO
dictcom.egg-info/SOURCES.txt
dictcom.egg-info/dependency_links.txt
dictcom.egg-info/requires.txt
dictcom.egg-info/top_level.txt