Metadata-Version: 1.0
Name: dictcom
Version: 0.0.3
Summary: A pseudo-API for Dictionary.com that works by scraping its website.
Home-page: https://github.com/mromnia/dictcom
Author: mromnia
Author-email: mr.omnia.dev@gmail.com
License: MIT
Platform: UNKNOWN
